Chessir/__init__.py
Chessir/board.py
Chessir/game.py
Chessir/moves.py
Chessir/square_attacked.py
chessir-0.1.1.dist-info/METADATA
chessir-0.1.1.dist-info/WHEEL
chessir-0.1.1.dist-info/RECORD
