Metadata-Version: 2.4
Name: Chessir
Version: 0.1.1
Summary: A chess board model that will import and export FEN, generate valid moves, and provide game status
Project-URL: Homepage, https://github.com/stuart-rickard/Chessir
Project-URL: Issues, https://github.com/stuart-rickard/Chessir/issues
Author-email: Stuart Rickard <dev@bau-dev.com>
License-Expression: Unlicense
Classifier: Operating System :: OS Independent
Classifier: Programming Language :: Python :: 3
Requires-Python: >=3.8
